{
  "updated_at": "2026/05/11 12:27",
  "updated_ts": 1778502468,
  "source": {
    "yahoo": "Yahoo Finance (yfinance)",
    "twse": "台灣證交所",
    "taifex": "台灣期交所"
  },
  "etf_0050_price": 96.9,
  "etf_0050_change": -0.1,
  "etf_006208_price": 224.45,
  "etf_006208_change": 0.07,
  "usd_twd": 31.366,
  "twd_trend": "升值",
  "score_usd_twd": 6.6,
  "vix": 18.2,
  "vix_status": "平穩",
  "score_vix": 7,
  "sox": 11775.5,
  "sox_change": 5.51,
  "score_sox": 10.0,
  "nasdaq": 26247.08,
  "nasdaq_change": 1.71,
  "twii": 41790.06,
  "twii_change": 0.45,
  "dxy": 98.03,
  "dxy_change": 0.2,
  "us10y": 4.364,
  "us10y_change": -0.64,
  "date_institutional": "2026/05/11",
  "foreign_net_buy": -5201771,
  "invest_net_buy": 0,
  "dealer_net_buy": 0,
  "score_foreign": 3.7,
  "score_invest": 5.0,
  "date_futures": "2026/05/11",
  "futures_foreign_net": 280,
  "score_futures": 5.0,
  "auto_scores": {
    "s13": 6.6,
    "s15": 7,
    "s16": 10.0,
    "s2": 3.7,
    "s3": 5.0,
    "s5": 5.0
  },
  "auto_score_count": 6,
  "total_score": 53,
  "all_scores": {
    "s1": 5,
    "s2": 3.7,
    "s3": 5.0,
    "s4": 5,
    "s5": 5.0,
    "s6": 5,
    "s7": 5,
    "s8": 5,
    "s9": 5,
    "s10": 5,
    "s11": 5,
    "s12": 5,
    "s13": 6.6,
    "s14": 5,
    "s15": 7,
    "s16": 10.0,
    "s17": 5,
    "s18": 5,
    "s19": 5,
    "s20": 5,
    "s21": 5,
    "s22": 5
  }
}